ccimport/__init__.py
ccimport/__version__.py
ccimport/buildmeta.py
ccimport/compat.py
ccimport/constants.py
ccimport/core.py
ccimport/extension.py
ccimport/global_cfg.py
ccimport/loader.py
ccimport/source_iter.py
ccimport/utils.py
ccimport/buildtools/__init__.py
ccimport/buildtools/writer.py
ccimport/ccpkg/__init__.py
ccimport-0.4.3.dist-info/LICENSE
ccimport-0.4.3.dist-info/METADATA
ccimport-0.4.3.dist-info/WHEEL
ccimport-0.4.3.dist-info/top_level.txt
ccimport-0.4.3.dist-info/RECORD
