Metadata-Version: 2.1
Name: ccimport
Version: 0.4.3
Summary: a tiny package for fast python c++ binding build.
Home-page: https://github.com/FindDefinition/ccimport
Author: Yan Yan
Author-email: yanyan.sub@outlook.com
License: MIT
Classifier: License :: OSI Approved :: MIT License
Classifier: Programming Language :: Python
Classifier: Programming Language :: Python :: 3
Classifier: Programming Language :: Python :: Implementation :: CPython
Classifier: Programming Language :: Python :: Implementation :: PyPy
Requires-Python: >=3.6
License-File: LICENSE
Requires-Dist: pybind11
Requires-Dist: ninja
Requires-Dist: requests
Requires-Dist: importlib-metadata >=2.0 ; python_version < "3.8"
Requires-Dist: dataclasses ; python_version == "3.6"
